README.md
setup.py
test/test_base.py
test/test_member.py
trello/__init__.py
trello/actions.py
trello/base.py
trello/batches.py
trello/boards.py
trello/cards.py
trello/checklists.py
trello/labels.py
trello/lists.py
trello/members.py
trello/notifications.py
trello/organizations.py
trello/search.py
trello/tokens.py
trello/types.py
trello/webhooks.py
trello.egg-info/PKG-INFO
trello.egg-info/SOURCES.txt
trello.egg-info/dependency_links.txt
trello.egg-info/requires.txt
trello.egg-info/top_level.txt