Metadata-Version: 1.2
Name: trello
Version: 0.9.5
Summary: Python library for interacting with the Trello API
Home-page: https://github.com/tghw/trello-py
Author: tghw,kulikjak,waghanza,lukegb
Author-email: ty@tghw.com
License: 
